aegir/__init__.py
aegir/aegir.py
aegir/exceptions.py
aegir/format_error.py
aegir/parsed_data.py
aegir/source_file.py
aegir/bot_items/__init__.py
aegir/bot_items/command.py
aegir/bot_items/decorator.py
aegir/bot_items/event.py
aegir/bot_items/listener.py
aegir/bot_items/main_file.py
aegir/util/__init__.py
aegir/util/action_type.py
aegir/util/decorator_util.py
aegir/util/import_util.py
aegir/util/run_mode.py
aegir_parser-0.2.0.dist-info/LICENSE
aegir_parser-0.2.0.dist-info/METADATA
aegir_parser-0.2.0.dist-info/WHEEL
aegir_parser-0.2.0.dist-info/top_level.txt
aegir_parser-0.2.0.dist-info/RECORD
